entsoe/__init__.py
entsoe/decorators.py
entsoe/entsoe.py
entsoe/exceptions.py
entsoe/mappings.py
entsoe/misc.py
entsoe/parsers.py
entsoe/py.typed
entsoe/series_parsers.py
entsoe/utils.py
entsoe/files/__init__.py
entsoe/files/decorators.py
entsoe/files/entsoe_files.py
entsoe/geo/__init__.py
entsoe/geo/utils.py
entsoe/geo/geojson/AT.geojson
entsoe/geo/geojson/BE.geojson
entsoe/geo/geojson/BG.geojson
entsoe/geo/geojson/CH.geojson
entsoe/geo/geojson/CZ.geojson
entsoe/geo/geojson/DE_LU.geojson
entsoe/geo/geojson/DK_1.geojson
entsoe/geo/geojson/DK_2.geojson
entsoe/geo/geojson/EE.geojson
entsoe/geo/geojson/ES.geojson
entsoe/geo/geojson/FI.geojson
entsoe/geo/geojson/FR.geojson
entsoe/geo/geojson/GR.geojson
entsoe/geo/geojson/HR.geojson
entsoe/geo/geojson/HU.geojson
entsoe/geo/geojson/IT_CALA.geojson
entsoe/geo/geojson/IT_CNOR.geojson
entsoe/geo/geojson/IT_CNOR_2020.geojson
entsoe/geo/geojson/IT_CSUD.geojson
entsoe/geo/geojson/IT_CSUD_2020.geojson
entsoe/geo/geojson/IT_NORD.geojson
entsoe/geo/geojson/IT_SARD.geojson
entsoe/geo/geojson/IT_SICI.geojson
entsoe/geo/geojson/IT_SUD.geojson
entsoe/geo/geojson/IT_SUD_2020.geojson
entsoe/geo/geojson/LT.geojson
entsoe/geo/geojson/LV.geojson
entsoe/geo/geojson/NL.geojson
entsoe/geo/geojson/NO_1.geojson
entsoe/geo/geojson/NO_2.geojson
entsoe/geo/geojson/NO_3.geojson
entsoe/geo/geojson/NO_4.geojson
entsoe/geo/geojson/NO_5.geojson
entsoe/geo/geojson/PL.geojson
entsoe/geo/geojson/PT.geojson
entsoe/geo/geojson/RO.geojson
entsoe/geo/geojson/RS.geojson
entsoe/geo/geojson/SE_1.geojson
entsoe/geo/geojson/SE_2.geojson
entsoe/geo/geojson/SE_3.geojson
entsoe/geo/geojson/SE_4.geojson
entsoe/geo/geojson/SI.geojson
entsoe/geo/geojson/SK.geojson
entsoe_py-0.7.7.dist-info/licenses/LICENSE
entsoe_py-0.7.7.dist-info/METADATA
entsoe_py-0.7.7.dist-info/WHEEL
entsoe_py-0.7.7.dist-info/top_level.txt
entsoe_py-0.7.7.dist-info/RECORD
