Metadata-Version: 2.4
Name: entsoe-py
Version: 0.7.7
Summary: A python API wrapper for ENTSO-E
Home-page: https://github.com/EnergieID/entsoe-py
Author: EnergieID.be, Frank Boerman
Author-email: jan@energieid.be, frank@fboerman.nl
License: MIT
Keywords: ENTSO-E data api energy
Classifier: Development Status :: 5 - Production/Stable
Classifier: Intended Audience :: Developers
Classifier: Topic :: Scientific/Engineering
Classifier: License :: OSI Approved :: MIT License
Classifier: Programming Language :: Python :: 3.9
Classifier: Programming Language :: Python :: 3.10
Classifier: Programming Language :: Python :: 3.11
License-File: LICENSE
Requires-Dist: requests
Requires-Dist: pytz
Requires-Dist: beautifulsoup4>=4.11.1
Requires-Dist: pandas>=2.2.0
Dynamic: author
Dynamic: author-email
Dynamic: classifier
Dynamic: description
Dynamic: description-content-type
Dynamic: home-page
Dynamic: keywords
Dynamic: license
Dynamic: license-file
Dynamic: requires-dist
Dynamic: summary
